psychopy_connect/__init__.py
psychopy_connect/serialdevice.py
psychopy_connect/components/__init__.py
psychopy_connect/components/parallelOut/__init__.py
psychopy_connect/components/parallelOut/classic/parallel.png
psychopy_connect/components/parallelOut/classic/parallel@2x.png
psychopy_connect/components/parallelOut/dark/parallel.png
psychopy_connect/components/parallelOut/dark/parallel@2x.png
psychopy_connect/components/parallelOut/light/parallel.png
psychopy_connect/components/parallelOut/light/parallel@2x.png
psychopy_connect/components/serialOut/__init__.py
psychopy_connect/components/serialOut/classic/serial.png
psychopy_connect/components/serialOut/classic/serial@2x.png
psychopy_connect/components/serialOut/dark/serial.png
psychopy_connect/components/serialOut/dark/serial@2x.png
psychopy_connect/components/serialOut/light/serial.png
psychopy_connect/components/serialOut/light/serial@2x.png
psychopy_connect/parallel/__init__.py
psychopy_connect/parallel/_dlportio.py
psychopy_connect/parallel/_inpout.py
psychopy_connect/parallel/_linux.py
psychopy_connect-0.0.2.dist-info/LICENSE
psychopy_connect-0.0.2.dist-info/METADATA
psychopy_connect-0.0.2.dist-info/WHEEL
psychopy_connect-0.0.2.dist-info/entry_points.txt
psychopy_connect-0.0.2.dist-info/top_level.txt
psychopy_connect-0.0.2.dist-info/RECORD
