Metadata-Version: 2.1
Name: psychopy-connect
Version: 0.0.2
Summary: Extension package for adding support to PsychoPy for connectivity i.e. serial and parallel ports.
Author-email: Jon Peirce <jon@opensceincetools.org>, Matthew Cutone <mcutone@opensceincetools.org>
License: GNU General Public License v3 (GPLv3)
Project-URL: homepage, https://github.com/psychopy/psychopy-connect
Project-URL: changelog, https://github.com/psychopy/psychopy-connect/blob/main/CHANGELOG.txt
Project-URL: documentation, https://pages.github.com/psychopy/psychopy-connect
Project-URL: repository, https://github.com/psychopy/psychopy-connect
Classifier: License :: OSI Approved :: GNU General Public License v3 (GPLv3)
Classifier: Programming Language :: Python :: 3
Classifier: Programming Language :: Python :: 3 :: Only
Classifier: Programming Language :: Python :: 3.7
Classifier: Programming Language :: Python :: 3.8
Classifier: Programming Language :: Python :: 3.9
Classifier: Programming Language :: Python :: 3.10
Classifier: Programming Language :: Python :: 3.11
Classifier: Programming Language :: Python :: Implementation :: CPython
Requires-Python: >=3.7
License-File: LICENSE
Requires-Dist: pyserial
Requires-Dist: psychopy-labhackers
Requires-Dist: psychopy-labjack
Requires-Dist: pyparallel ; sys_platform == "linux"
